ddnss.py
usr/lib/systemd/system/ddnss@.service
usr/lib/systemd/system/ddnss@.timer
usr/lib/sysusers.d/ddnss.conf
ddnss-1.0.5.dist-info/LICENSE.txt
ddnss-1.0.5.dist-info/METADATA
ddnss-1.0.5.dist-info/WHEEL
ddnss-1.0.5.dist-info/entry_points.txt
ddnss-1.0.5.dist-info/top_level.txt
ddnss-1.0.5.dist-info/RECORD
