Metadata-Version: 2.1
Name: ddnss
Version: 1.0.5
Summary: Update DynDNS hosts registered at ddnss.de.
Home-page: https://github.com/conqp/ddnss
Author: Richard Neumann
Author-email: mail@richard-neumann.de
License: GPLv3
Keywords: dnamic DNS DynDNS ddnss update script client
Platform: UNKNOWN
Requires-Python: >=3.8
